spacepy/LANLstar.py
spacepy/__init__.py
spacepy/ae9ap9.py
spacepy/coordinates.py
spacepy/datamanager.py
spacepy/datamodel.py
spacepy/dllcdf.dll
spacepy/empiricals.py
spacepy/igrf.py
spacepy/lib.py
spacepy/libspacepy.dll.a
spacepy/omni.py
spacepy/poppy.py
spacepy/rst.py
spacepy/seapy.py
spacepy/time.py
spacepy/ctrans/__init__.py
spacepy/ctrans/iau80n.py
spacepy/data/SEA_epochs_OMNI.txt
spacepy/data/igrf13coeffs.txt
spacepy/data/spacepy.mplstyle
spacepy/data/spacepy_altgrid.mplstyle
spacepy/data/spacepy_polar.mplstyle
spacepy/data/tai-utc.dat
spacepy/data/LANLstar/LANLstar_OPDyn.txt
spacepy/data/LANLstar/LANLstar_OPQuiet.txt
spacepy/data/LANLstar/LANLstar_RAMSCB.txt
spacepy/data/LANLstar/LANLstar_T01QUIET.txt
spacepy/data/LANLstar/LANLstar_T01STORM.txt
spacepy/data/LANLstar/LANLstar_T05.txt
spacepy/data/LANLstar/LANLstar_T89.txt
spacepy/data/LANLstar/LANLstar_T96.txt
spacepy/data/LANLstar/Lmax_OPDyn.txt
spacepy/data/LANLstar/Lmax_OPQuiet.txt
spacepy/data/LANLstar/Lmax_T01QUIET.txt
spacepy/data/LANLstar/Lmax_T01STORM.txt
spacepy/data/LANLstar/Lmax_T05.txt
spacepy/data/LANLstar/Lmax_T89.txt
spacepy/data/LANLstar/Lmax_T96.txt
spacepy/data/TS07D/TAIL_PAR/tailamebhr1.par
spacepy/data/TS07D/TAIL_PAR/tailamebhr2.par
spacepy/data/TS07D/TAIL_PAR/tailamebhr3.par
spacepy/data/TS07D/TAIL_PAR/tailamebhr4.par
spacepy/data/TS07D/TAIL_PAR/tailamebhr5.par
spacepy/data/TS07D/TAIL_PAR/tailamhr_e_11.par
spacepy/data/TS07D/TAIL_PAR/tailamhr_e_12.par
spacepy/data/TS07D/TAIL_PAR/tailamhr_e_13.par
spacepy/data/TS07D/TAIL_PAR/tailamhr_e_14.par
spacepy/data/TS07D/TAIL_PAR/tailamhr_e_21.par
spacepy/data/TS07D/TAIL_PAR/tailamhr_e_22.par
spacepy/data/TS07D/TAIL_PAR/tailamhr_e_23.par
spacepy/data/TS07D/TAIL_PAR/tailamhr_e_24.par
spacepy/data/TS07D/TAIL_PAR/tailamhr_e_31.par
spacepy/data/TS07D/TAIL_PAR/tailamhr_e_32.par
spacepy/data/TS07D/TAIL_PAR/tailamhr_e_33.par
spacepy/data/TS07D/TAIL_PAR/tailamhr_e_34.par
spacepy/data/TS07D/TAIL_PAR/tailamhr_e_41.par
spacepy-0.7.0.dist-info/LICENSE.md
spacepy-0.7.0.dist-info/METADATA
spacepy-0.7.0.dist-info/WHEEL
spacepy-0.7.0.dist-info/top_level.txt
spacepy-0.7.0.dist-info/RECORD
