Metadata-Version: 2.1
Name: spacepy
Version: 0.7.0
Summary: SpacePy: Tools for Space Science Applications
Home-page: https://github.com/spacepy/spacepy
Author: SpacePy team
Author-email: SpacePy team <spacepy@lanl.gov>
Maintainer: Steve Morley, Dan Welling, Brian Larsen, Jon Niehof
Maintainer-email: Steve Morley <smorley@lanl.gov>, Dan Welling <dwelling@umich.edu>, Brian Larsen <balarsen@lanl.gov>, Jon Niehof <Jonathan.Niehof@unh.edu>
License: Copyright 2010 Triad National Security, LLC
Project-URL: homepage, https://spacepy.github.io/
Project-URL: repository, https://github.com/spacepy/spacepy.git
Keywords: magnetosphere,plasma,physics,space,solar.wind,space.weather,magnetohydrodynamics
Platform: Windows
Platform: Linux
Platform: MacOS X
Platform: Unix
Classifier: Development Status :: 4 - Beta
Classifier: Intended Audience :: Science/Research
Classifier: License :: OSI Approved :: Python Software Foundation License
Classifier: Operating System :: MacOS :: MacOS X
Classifier: Operating System :: Microsoft :: Windows
Classifier: Operating System :: POSIX
Classifier: Operating System :: POSIX :: Linux
Classifier: Programming Language :: C
Classifier: Programming Language :: Fortran
Classifier: Programming Language :: Python
Classifier: Programming Language :: Python :: 3
Classifier: Programming Language :: Python :: 3 :: Only
Classifier: Topic :: Scientific/Engineering :: Astronomy
Classifier: Topic :: Scientific/Engineering :: Atmospheric Science
Classifier: Topic :: Scientific/Engineering :: Physics
Classifier: Topic :: Scientific/Engineering :: Visualization
Classifier: Topic :: Software Development :: Libraries :: Python Modules
Requires-Python: >=3.7
License-File: LICENSE.md
Requires-Dist: numpy>=1.15.1
Requires-Dist: scipy>=1.0
Requires-Dist: matplotlib>=3.1
Requires-Dist: h5py>=2.10
Requires-Dist: python-dateutil>=2.5
